connected_things/__init__.py
connected_things/connected_things.py
connected_things-0.0.1.dist-info/METADATA
connected_things-0.0.1.dist-info/WHEEL
connected_things-0.0.1.dist-info/top_level.txt
connected_things-0.0.1.dist-info/RECORD
